django_postgres_backup/__init__.py
django_postgres_backup/apps.py
django_postgres_backup/common.py
django_postgres_backup/management/__init__.py
django_postgres_backup/management/commands/__init__.py
django_postgres_backup/management/commands/postgres_backup.py
django_postgres_backup/management/commands/postgres_restore.py
django_postgres_backup/settings.py
django_postgres_backup/tests/__init__.py
django_postgres_backup/tests/test_commands.py
django_postgres_backup-1.0.0.dist-info/LICENSE
django_postgres_backup-1.0.0.dist-info/WHEEL
django_postgres_backup-1.0.0.dist-info/METADATA
django_postgres_backup-1.0.0.dist-info/RECORD
