Metadata-Version: 2.1
Name: django-postgres-backup
Version: 1.0.0
Summary: Django managed commands to back up and restore a PostgreSQL database with multiple backup generations.
Home-page: https://github.com/itell-solutions/django_postgres_backup
License: MIT
Keywords: backup,django,postgres,restore
Author: ITELL.SOLUTIONS GmbH
Requires-Python: >=3.8,<4
Classifier: Development Status :: 5 - Production/Stable
Classifier: Environment :: Console
Classifier: Framework :: Django
Classifier: Framework :: Django :: 4
Classifier: Intended Audience :: Developers
Classifier: License :: OSI Approved :: MIT License
Classifier: Natural Language :: English
Classifier: Operating System :: OS Independent
Classifier: Programming Language :: Python :: 3
Classifier: Programming Language :: Python :: 3.8
Classifier: Programming Language :: Python :: 3.9
Classifier: Programming Language :: Python :: 3.10
Classifier: Programming Language :: Python :: 3.11
Classifier: Programming Language :: Python :: 3 :: Only
Classifier: Programming Language :: Python :: 3.10
Classifier: Programming Language :: Python :: 3.8
Classifier: Programming Language :: Python :: 3.9
Classifier: Topic :: Database
Classifier: Topic :: System :: Archiving :: Backup
Requires-Dist: Django (>=4.1,<5.0)
Requires-Dist: django-extensions (>=3.1.5,<4.0.0)
Requires-Dist: django-libsass (>=0.9,<0.10)
Requires-Dist: psycopg2-binary (>=2.9.3,<3.0.0)
Requires-Dist: pytest (>=7.1.3,<8.0.0)
Requires-Dist: requests (>=2.27.1,<3.0.0)
Project-URL: Changes, https://github.com/itell-solutions/django_postgres_backup/blob/main/CHANGES.md
Project-URL: Issue Tracker, https://github.com/itell-solutions/django_postgres_backup/issues
Project-URL: Repository, https://github.com/itell-solutions/django_postgres_backup
